stone/__init__.py
stone/__main__.py
stone/config.py
stone/page.py
stone/plugins.py
stone/resource.py
stone/site.py
stone/stone.py
stone/backends/__init__.py
stone/backends/file.py
stone/backends/s3.py
stone/generators/__init__.py
stone/generators/abc.py
stone/generators/blog.py
stone/generators/single.py
stone/renderers/__init__.py
stone/renderers/jinja2.py
stone/renderers/markdown.py
stone_site-0.1.8.dist-info/LICENSE
stone_site-0.1.8.dist-info/METADATA
stone_site-0.1.8.dist-info/WHEEL
stone_site-0.1.8.dist-info/entry_points.txt
stone_site-0.1.8.dist-info/top_level.txt
stone_site-0.1.8.dist-info/RECORD
