Metadata-Version: 2.1
Name: stone-site
Version: 0.1.8
Summary: Static site generator
Home-page: https://github.com/NeuralSandwich/stone
Author: Sean Jones
Author-email: sean@half.systems
License: MIT
Keywords: web html markdown static content
Platform: UNKNOWN
Classifier: Development Status :: 3 - Alpha
Classifier: Intended Audience :: Developers
Classifier: License :: OSI Approved :: MIT License
Classifier: Programming Language :: Python :: 3
Classifier: Programming Language :: Python :: 3.3
Classifier: Programming Language :: Python :: 3.4
Classifier: Programming Language :: Python :: 3.5
Requires-Dist: jinja2
Requires-Dist: unidecode
Provides-Extra: dev
Requires-Dist: check-manifest; extra == 'dev'
Provides-Extra: test
Requires-Dist: coverage; extra == 'test'
